[1,["1ba932cb7@6c48a"],["_textureSource"],["cc.SpriteFrame","cc.SpriteAtlas"],0,[[[{"name":"btn_ok","rect":{"x":681,"y":487,"width":117,"height":53},"offset":{"x":0,"y":0},"originalSize":{"width":117,"height":53},"rotated":true,"capInsets":[0,0,0,0],"packable":true,"pixelsToUnit":100,"pivot":{"x":0.5,"y":0.5},"meshType":0}],[0],0,[0],[0],[0]],[[{"name":"head-1001","rect":{"x":681,"y":610,"width":64,"height":54},"offset":{"x":0,"y":-4.5},"originalSize":{"width":64,"height":63},"rotated":true,"capInsets":[0,0,0,0],"packable":true,"pixelsToUnit":100,"pivot":{"x":0.5,"y":0.5},"meshType":0}],[0],0,[0],[0],[0]],[[{"name":"bg_window","rect":{"x":525,"y":3,"width":478,"height":320},"offset":{"x":0,"y":0},"originalSize":{"width":478,"height":320},"rotated":true,"capInsets":[0,0,0,0],"packable":true,"pixelsToUnit":100,"pivot":{"x":0.5,"y":0.5},"meshType":0}],[0],0,[0],[0],[0]],[[{"name":"silver","rect":{"x":740,"y":535,"width":26,"height":25},"offset":{"x":0,"y":-0.5},"originalSize":{"width":32,"height":32},"rotated":false,"capInsets":[0,0,0,0],"packable":true,"pixelsToUnit":100,"pivot":{"x":0.5,"y":0.5},"meshType":0}],[0],0,[0],[0],[0]],[[{"name":"coin","rect":{"x":740,"y":487,"width":42,"height":43},"offset":{"x":0,"y":0},"originalSize":{"width":42,"height":43},"rotated":true,"capInsets":[0,0,0,0],"packable":true,"pixelsToUnit":100,"pivot":{"x":0.5,"y":0.5},"meshType":0}],[0],0,[0],[0],[0]],[[{"name":"head_frame-1001","rect":{"x":3,"y":3,"width":516,"height":516},"offset":{"x":0,"y":0},"originalSize":{"width":600,"height":600},"rotated":false,"capInsets":[0,0,0,0],"packable":true,"pixelsToUnit":100,"pivot":{"x":0.5,"y":0.5},"meshType":0}],[0],0,[0],[0],[0]],[[{"name":"toast","rect":{"x":3,"y":525,"width":528,"height":90},"offset":{"x":0.5,"y":0},"originalSize":{"width":539,"height":90},"rotated":false,"capInsets":[0,0,0,0],"packable":true,"pixelsToUnit":100,"pivot":{"x":0.5,"y":0.5},"meshType":0}],[0],0,[0],[0],[0]],[[{"name":"auto-atlas","spriteFrames":["head_frame-1001","aa+X1s+ptGdJDpSD8KcgFf@f9941","toast","bdxsVkrYFGUatxXIHq1BIt@f9941","bg_window","18eXBo6YpDpqSBr95RwzNh@f9941","loading","f5uEalmxxLta5OFiwnmvRy@f9941","btn_ok","08d/3UVgVB5rZDvkkE1Qa3@f9941","head-1001","12YaUgc4xMgKHlBKARiAbA@f9941","coin","50GAtDmTRKY5fbApGNm+i5@f9941","silver","4bMmHfbfVEqK7J98ehcuix@f9941"]}],[1],0,[],[],[]],[[{"name":"loading","rect":{"x":537,"y":487,"width":138,"height":138},"offset":{"x":0,"y":0},"originalSize":{"width":138,"height":138},"rotated":false,"capInsets":[0,0,0,0],"packable":true,"pixelsToUnit":100,"pivot":{"x":0.5,"y":0.5},"meshType":0}],[0],0,[0],[0],[0]]]]
